{
  "klass": "Specie",
  "id": 84,
  "dbSymbol": "doduo",
  "forms": [
    {
      "form": 0,
      "height": 1.4,
      "weight": 39.2,
      "type1": "normal",
      "type2": "flying",
      "baseHp": 35,
      "baseAtk": 85,
      "baseDfe": 45,
      "baseSpd": 75,
      "baseAts": 35,
      "baseDfs": 35,
      "evHp": 0,
      "evAtk": 1,
      "evDfe": 0,
      "evSpd": 0,
      "evAts": 0,
      "evDfs": 0,
      "evolutions": [
        {
          "dbSymbol": "dodrio",
          "form": 0,
          "conditions": [
            {
              "type": "minLevel",
              "value": 31
            }
          ]
        }
      ],
      "experienceType": 1,
      "baseExperience": 62,
      "baseLoyalty": 50,
      "catchRate": 190,
      "femaleRate": 50,
      "breedGroups": [
        4,
        4
      ],
      "hatchSteps": 2560,
      "babyDbSymbol": "doduo",
      "babyForm": 0,
      "itemHeld": [
        {
          "dbSymbol": "none",
          "chance": 0
        },
        {
          "dbSymbol": "none",
          "chance": 0
        }
      ],
      "abilities": [
        "early_bird",
        "run_away",
        "tangled_feet"
      ],
      "frontOffsetY": 0,
      "resources": {
        "icon": "0084",
        "iconF": "0084",
        "iconShiny": "0084s",
        "iconShinyF": "0084s",
        "front": "0084",
        "frontF": "0084f",
        "frontShiny": "0084s",
        "frontShinyF": "0084sf",
        "back": "0084",
        "backF": "0084f",
        "backShiny": "0084s",
        "backShinyF": "0084sf",
        "footprint": "0084",
        "character": "0084",
        "characterF": "0084",
        "characterShiny": "0084s",
        "characterShinyF": "0084s",
        "cry": "0084.ogg",
        "hasFemale": true,
        "egg": "egg",
        "iconEgg": "egg"
      },
      "moveSet": [
        {
          "move": "growl",
          "klass": "LevelLearnableMove",
          "level": 1
        },
        {
          "move": "peck",
          "klass": "LevelLearnableMove",
          "level": 1
        },
        {
          "move": "quick_attack",
          "klass": "LevelLearnableMove",
          "level": 5
        },
        {
          "move": "fury_attack",
          "klass": "LevelLearnableMove",
          "level": 9
        },
        {
          "move": "pluck",
          "klass": "LevelLearnableMove",
          "level": 14
        },
        {
          "move": "double_hit",
          "klass": "LevelLearnableMove",
          "level": 19
        },
        {
          "move": "agility",
          "klass": "LevelLearnableMove",
          "level": 23
        },
        {
          "move": "uproar",
          "klass": "LevelLearnableMove",
          "level": 27
        },
        {
          "move": "acupressure",
          "klass": "LevelLearnableMove",
          "level": 30
        },
        {
          "move": "swords_dance",
          "klass": "LevelLearnableMove",
          "level": 33
        },
        {
          "move": "drill_peck",
          "klass": "LevelLearnableMove",
          "level": 36
        },
        {
          "move": "endeavor",
          "klass": "LevelLearnableMove",
          "level": 39
        },
        {
          "move": "thrash",
          "klass": "LevelLearnableMove",
          "level": 43
        },
        {
          "move": "swords_dance",
          "klass": "TechLearnableMove"
        },
        {
          "move": "whirlwind",
          "klass": "BreedLearnableMove"
        },
        {
          "move": "body_slam",
          "klass": "TechLearnableMove"
        },
        {
          "move": "take_down",
          "klass": "TechLearnableMove"
        },
        {
          "move": "double_edge",
          "klass": "TechLearnableMove"
        },
        {
          "move": "low_kick",
          "klass": "TechLearnableMove"
        },
        {
          "move": "agility",
          "klass": "TechLearnableMove"
        },
        {
          "move": "swift",
          "klass": "TechLearnableMove"
        },
        {
          "move": "sky_attack",
          "klass": "BreedLearnableMove"
        },
        {
          "move": "rest",
          "klass": "TechLearnableMove"
        },
        {
          "move": "substitute",
          "klass": "TechLearnableMove"
        },
        {
          "move": "thief",
          "klass": "TechLearnableMove"
        },
        {
          "move": "flail",
          "klass": "BreedLearnableMove"
        },
        {
          "move": "protect",
          "klass": "TechLearnableMove"
        },
        {
          "move": "mud_slap",
          "klass": "TechLearnableMove"
        },
        {
          "move": "endure",
          "klass": "TechLearnableMove"
        },
        {
          "move": "sleep_talk",
          "klass": "TechLearnableMove"
        },
        {
          "move": "baton_pass",
          "klass": "TechLearnableMove"
        },
        {
          "move": "rain_dance",
          "klass": "TechLearnableMove"
        },
        {
          "move": "sunny_day",
          "klass": "TechLearnableMove"
        },
        {
          "move": "uproar",
          "klass": "TechLearnableMove"
        },
        {
          "move": "facade",
          "klass": "TechLearnableMove"
        },
        {
          "move": "helping_hand",
          "klass": "TechLearnableMove"
        },
        {
          "move": "knock_off",
          "klass": "TechLearnableMove"
        },
        {
          "move": "endeavor",
          "klass": "TechLearnableMove"
        },
        {
          "move": "feather_dance",
          "klass": "TechLearnableMove"
        },
        {
          "move": "aerial_ace",
          "klass": "TechLearnableMove"
        },
        {
          "move": "tailwind",
          "klass": "TechLearnableMove"
        },
        {
          "move": "assurance",
          "klass": "BreedLearnableMove"
        },
        {
          "move": "brave_bird",
          "klass": "TechLearnableMove"
        },
        {
          "move": "acrobatics",
          "klass": "TechLearnableMove"
        },
        {
          "move": "throat_chop",
          "klass": "TechLearnableMove"
        },
        {
          "move": "lunge",
          "klass": "TechLearnableMove"
        },
        {
          "move": "tera_blast",
          "klass": "TechLearnableMove"
        },
        {
          "move": "fly",
          "klass": "TechLearnableMove"
        }
      ],
      "formTextId": {
        "name": 120,
        "description": 0
      }
    }
  ]
}