{
  "klass": "Specie",
  "id": 989,
  "dbSymbol": "sandy_shocks",
  "forms": [
    {
      "form": 0,
      "height": 2.3,
      "weight": 60.0,
      "type1": "electric",
      "type2": "ground",
      "baseHp": 85,
      "baseAtk": 81,
      "baseDfe": 97,
      "baseAts": 121,
      "baseDfs": 85,
      "baseSpd": 101,
      "evHp": 0,
      "evAtk": 0,
      "evDfe": 0,
      "evAts": 3,
      "evDfs": 0,
      "evSpd": 0,
      "evolutions": [],
      "experienceType": 2,
      "baseExperience": 285,
      "baseLoyalty": 0,
      "catchRate": 30,
      "femaleRate": -1,
      "breedGroups": [
        15,
        15
      ],
      "hatchSteps": 6400,
      "babyDbSymbol": "sandy_shocks",
      "babyForm": 0,
      "itemHeld": [
        {
          "dbSymbol": "none",
          "chance": 0
        },
        {
          "dbSymbol": "none",
          "chance": 0
        }
      ],
      "abilities": [
        "protosynthesis",
        "protosynthesis",
        "protosynthesis"
      ],
      "frontOffsetY": 0,
      "resources": {
        "icon": "0989",
        "iconShiny": "0989s",
        "front": "0989",
        "frontShiny": "0989s",
        "back": "0989",
        "backShiny": "0989s",
        "footprint": "0989",
        "character": "0989",
        "characterShiny": "0989s",
        "cry": "0989.ogg",
        "hasFemale": false,
        "egg": "egg",
        "iconEgg": "egg"
      },
      "moveSet": [
        {
          "move": "supersonic",
          "klass": "LevelLearnableMove",
          "level": 1
        },
        {
          "move": "thunder_shock",
          "klass": "LevelLearnableMove",
          "level": 1
        },
        {
          "move": "thunder_wave",
          "klass": "LevelLearnableMove",
          "level": 1
        },
        {
          "move": "electric_terrain",
          "klass": "LevelLearnableMove",
          "level": 1
        },
        {
          "move": "spark",
          "klass": "LevelLearnableMove",
          "level": 7
        },
        {
          "move": "bulldoze",
          "klass": "LevelLearnableMove",
          "level": 14
        },
        {
          "move": "charge_beam",
          "klass": "LevelLearnableMove",
          "level": 21
        },
        {
          "move": "tri_attack",
          "klass": "LevelLearnableMove",
          "level": 28
        },
        {
          "move": "screech",
          "klass": "LevelLearnableMove",
          "level": 35
        },
        {
          "move": "heavy_slam",
          "klass": "LevelLearnableMove",
          "level": 42
        },
        {
          "move": "metal_sound",
          "klass": "LevelLearnableMove",
          "level": 49
        },
        {
          "move": "discharge",
          "klass": "LevelLearnableMove",
          "level": 56
        },
        {
          "move": "earth_power",
          "klass": "LevelLearnableMove",
          "level": 63
        },
        {
          "move": "mirror_coat",
          "klass": "LevelLearnableMove",
          "level": 70
        },
        {
          "move": "gravity",
          "klass": "LevelLearnableMove",
          "level": 77
        },
        {
          "move": "zap_cannon",
          "klass": "LevelLearnableMove",
          "level": 84
        },
        {
          "move": "magnetic_flux",
          "klass": "LevelLearnableMove",
          "level": 91
        },
        {
          "move": "body_slam",
          "klass": "TechLearnableMove"
        },
        {
          "move": "take_down",
          "klass": "TechLearnableMove"
        },
        {
          "move": "hyper_beam",
          "klass": "TechLearnableMove"
        },
        {
          "move": "thunderbolt",
          "klass": "TechLearnableMove"
        },
        {
          "move": "thunder_wave",
          "klass": "TechLearnableMove"
        },
        {
          "move": "thunder",
          "klass": "TechLearnableMove"
        },
        {
          "move": "earthquake",
          "klass": "TechLearnableMove"
        },
        {
          "move": "light_screen",
          "klass": "TechLearnableMove"
        },
        {
          "move": "reflect",
          "klass": "TechLearnableMove"
        },
        {
          "move": "swift",
          "klass": "TechLearnableMove"
        },
        {
          "move": "rest",
          "klass": "TechLearnableMove"
        },
        {
          "move": "substitute",
          "klass": "TechLearnableMove"
        },
        {
          "move": "protect",
          "klass": "TechLearnableMove"
        },
        {
          "move": "spikes",
          "klass": "TechLearnableMove"
        },
        {
          "move": "sandstorm",
          "klass": "TechLearnableMove"
        },
        {
          "move": "endure",
          "klass": "TechLearnableMove"
        },
        {
          "move": "sleep_talk",
          "klass": "TechLearnableMove"
        },
        {
          "move": "sunny_day",
          "klass": "BreedLearnableMove"
        },
        {
          "move": "sunny_day",
          "klass": "TechLearnableMove"
        },
        {
          "move": "facade",
          "klass": "TechLearnableMove"
        },
        {
          "move": "charge",
          "klass": "TechLearnableMove"
        },
        {
          "move": "metal_sound",
          "klass": "TechLearnableMove"
        },
        {
          "move": "sand_tomb",
          "klass": "TechLearnableMove"
        },
        {
          "move": "iron_defense",
          "klass": "TechLearnableMove"
        },
        {
          "move": "mud_shot",
          "klass": "TechLearnableMove"
        },
        {
          "move": "gravity",
          "klass": "TechLearnableMove"
        },
        {
          "move": "power_gem",
          "klass": "TechLearnableMove"
        },
        {
          "move": "earth_power",
          "klass": "TechLearnableMove"
        },
        {
          "move": "giga_impact",
          "klass": "TechLearnableMove"
        },
        {
          "move": "flash_cannon",
          "klass": "TechLearnableMove"
        },
        {
          "move": "stealth_rock",
          "klass": "TechLearnableMove"
        },
        {
          "move": "charge_beam",
          "klass": "TechLearnableMove"
        },
        {
          "move": "heavy_slam",
          "klass": "TechLearnableMove"
        },
        {
          "move": "electro_ball",
          "klass": "TechLearnableMove"
        },
        {
          "move": "volt_switch",
          "klass": "TechLearnableMove"
        },
        {
          "move": "bulldoze",
          "klass": "TechLearnableMove"
        },
        {
          "move": "electroweb",
          "klass": "TechLearnableMove"
        },
        {
          "move": "wild_charge",
          "klass": "TechLearnableMove"
        },
        {
          "move": "eerie_impulse",
          "klass": "TechLearnableMove"
        },
        {
          "move": "electric_terrain",
          "klass": "TechLearnableMove"
        },
        {
          "move": "high_horsepower",
          "klass": "TechLearnableMove"
        },
        {
          "move": "stomping_tantrum",
          "klass": "TechLearnableMove"
        },
        {
          "move": "body_press",
          "klass": "TechLearnableMove"
        },
        {
          "move": "scorching_sands",
          "klass": "TechLearnableMove"
        },
        {
          "move": "tera_blast",
          "klass": "TechLearnableMove"
        },
        {
          "move": "supercell_slam",
          "klass": "TechLearnableMove"
        }
      ],
      "formTextId": {
        "name": 1303,
        "description": 0
      }
    }
  ]
}