{
  "klass": "Specie",
  "id": 562,
  "dbSymbol": "yamask",
  "forms": [
    {
      "form": 0,
      "formTextId": {
        "name": 735,
        "description": 0
      },
      "height": 0.5,
      "weight": 1.5,
      "type1": "ghost",
      "type2": "__undef__",
      "baseHp": 38,
      "baseAtk": 30,
      "baseDfe": 85,
      "baseSpd": 30,
      "baseAts": 55,
      "baseDfs": 65,
      "evHp": 0,
      "evAtk": 0,
      "evDfe": 1,
      "evSpd": 0,
      "evAts": 0,
      "evDfs": 0,
      "evolutions": [
        {
          "dbSymbol": "cofagrigus",
          "form": 0,
          "conditions": [
            {
              "type": "minLevel",
              "value": 34
            }
          ]
        }
      ],
      "experienceType": 1,
      "baseExperience": 61,
      "baseLoyalty": 50,
      "catchRate": 190,
      "femaleRate": 50,
      "breedGroups": [
        10,
        11
      ],
      "hatchSteps": 3200,
      "babyDbSymbol": "yamask",
      "babyForm": 0,
      "itemHeld": [
        {
          "dbSymbol": "none",
          "chance": 0
        },
        {
          "dbSymbol": "none",
          "chance": 0
        }
      ],
      "abilities": [
        "mummy",
        "mummy",
        "mummy"
      ],
      "frontOffsetY": 25,
      "resources": {
        "icon": "0562",
        "iconShiny": "0562s",
        "front": "0562",
        "frontShiny": "0562s",
        "back": "0562",
        "backShiny": "0562s",
        "footprint": "0562",
        "character": "0562",
        "characterShiny": "0562s",
        "cry": "0562.ogg",
        "hasFemale": false,
        "egg": "egg",
        "iconEgg": "egg"
      },
      "moveSet": [
        {
          "move": "protect",
          "klass": "LevelLearnableMove",
          "level": 1
        },
        {
          "move": "astonish",
          "klass": "LevelLearnableMove",
          "level": 1
        },
        {
          "move": "haze",
          "klass": "LevelLearnableMove",
          "level": 4
        },
        {
          "move": "night_shade",
          "klass": "LevelLearnableMove",
          "level": 8
        },
        {
          "move": "disable",
          "klass": "LevelLearnableMove",
          "level": 12
        },
        {
          "move": "will_o_wisp",
          "klass": "LevelLearnableMove",
          "level": 16
        },
        {
          "move": "crafty_shield",
          "klass": "LevelLearnableMove",
          "level": 20
        },
        {
          "move": "hex",
          "klass": "LevelLearnableMove",
          "level": 24
        },
        {
          "move": "mean_look",
          "klass": "LevelLearnableMove",
          "level": 28
        },
        {
          "move": "grudge",
          "klass": "LevelLearnableMove",
          "level": 32
        },
        {
          "move": "curse",
          "klass": "LevelLearnableMove",
          "level": 36
        },
        {
          "move": "shadow_ball",
          "klass": "LevelLearnableMove",
          "level": 40
        },
        {
          "move": "dark_pulse",
          "klass": "LevelLearnableMove",
          "level": 44
        },
        {
          "move": "guard_split",
          "klass": "LevelLearnableMove",
          "level": 48
        },
        {
          "move": "power_split",
          "klass": "LevelLearnableMove",
          "level": 48
        },
        {
          "move": "destiny_bond",
          "klass": "LevelLearnableMove",
          "level": 52
        },
        {
          "move": "psychic",
          "klass": "TechLearnableMove"
        },
        {
          "move": "rest",
          "klass": "TechLearnableMove"
        },
        {
          "move": "substitute",
          "klass": "TechLearnableMove"
        },
        {
          "move": "thief",
          "klass": "TechLearnableMove"
        },
        {
          "move": "snore",
          "klass": "TechLearnableMove"
        },
        {
          "move": "protect",
          "klass": "TechLearnableMove"
        },
        {
          "move": "endure",
          "klass": "TechLearnableMove"
        },
        {
          "move": "attract",
          "klass": "TechLearnableMove"
        },
        {
          "move": "sleep_talk",
          "klass": "TechLearnableMove"
        },
        {
          "move": "safeguard",
          "klass": "TechLearnableMove"
        },
        {
          "move": "rain_dance",
          "klass": "TechLearnableMove"
        },
        {
          "move": "shadow_ball",
          "klass": "TechLearnableMove"
        },
        {
          "move": "will_o_wisp",
          "klass": "TechLearnableMove"
        },
        {
          "move": "memento",
          "klass": "BreedLearnableMove"
        },
        {
          "move": "facade",
          "klass": "TechLearnableMove"
        },
        {
          "move": "trick",
          "klass": "TechLearnableMove"
        },
        {
          "move": "skill_swap",
          "klass": "TechLearnableMove"
        },
        {
          "move": "imprison",
          "klass": "TechLearnableMove"
        },
        {
          "move": "fake_tears",
          "klass": "TechLearnableMove"
        },
        {
          "move": "iron_defense",
          "klass": "TechLearnableMove"
        },
        {
          "move": "calm_mind",
          "klass": "TechLearnableMove"
        },
        {
          "move": "payback",
          "klass": "TechLearnableMove"
        },
        {
          "move": "toxic_spikes",
          "klass": "TechLearnableMove"
        },
        {
          "move": "dark_pulse",
          "klass": "TechLearnableMove"
        },
        {
          "move": "energy_ball",
          "klass": "TechLearnableMove"
        },
        {
          "move": "nasty_plot",
          "klass": "TechLearnableMove"
        },
        {
          "move": "zen_headbutt",
          "klass": "TechLearnableMove"
        },
        {
          "move": "trick_room",
          "klass": "TechLearnableMove"
        },
        {
          "move": "wonder_room",
          "klass": "TechLearnableMove"
        },
        {
          "move": "round",
          "klass": "TechLearnableMove"
        },
        {
          "move": "ally_switch",
          "klass": "TechLearnableMove"
        },
        {
          "move": "hex",
          "klass": "TechLearnableMove"
        },
        {
          "move": "poltergeist",
          "klass": "TutorLearnableMove"
        },
        {
          "move": "flash",
          "klass": "TechLearnableMove"
        }
      ]
    },
    {
      "form": 1,
      "formTextId": {
        "name": 736,
        "description": 175
      },
      "height": 0.5,
      "weight": 1.5,
      "type1": "ground",
      "type2": "ghost",
      "baseHp": 38,
      "baseAtk": 55,
      "baseDfe": 85,
      "baseSpd": 30,
      "baseAts": 30,
      "baseDfs": 65,
      "evHp": 0,
      "evAtk": 0,
      "evDfe": 1,
      "evSpd": 0,
      "evAts": 0,
      "evDfs": 0,
      "evolutions": [
        {
          "dbSymbol": "runerigus",
          "form": 0,
          "conditions": [
            {
              "type": "minLevel",
              "value": 34
            }
          ]
        }
      ],
      "experienceType": 1,
      "baseExperience": 61,
      "baseLoyalty": 50,
      "catchRate": 190,
      "femaleRate": 50,
      "breedGroups": [
        10,
        11
      ],
      "hatchSteps": 3200,
      "babyDbSymbol": "yamask",
      "babyForm": 1,
      "itemHeld": [
        {
          "dbSymbol": "none",
          "chance": 0
        },
        {
          "dbSymbol": "none",
          "chance": 0
        }
      ],
      "abilities": [
        "wandering_spirit",
        "wandering_spirit",
        "wandering_spirit"
      ],
      "frontOffsetY": 25,
      "resources": {
        "icon": "0562_01",
        "iconShiny": "0562s_01",
        "front": "0562_01",
        "frontShiny": "0562s_01",
        "back": "0562_01",
        "backShiny": "0562s_01",
        "footprint": "0562",
        "character": "0562_01",
        "characterShiny": "0562s_01",
        "cry": "0562.ogg",
        "hasFemale": false,
        "egg": "egg",
        "iconEgg": "egg"
      },
      "moveSet": [
        {
          "move": "protect",
          "klass": "LevelLearnableMove",
          "level": 1
        },
        {
          "move": "astonish",
          "klass": "LevelLearnableMove",
          "level": 1
        },
        {
          "move": "haze",
          "klass": "LevelLearnableMove",
          "level": 4
        },
        {
          "move": "night_shade",
          "klass": "LevelLearnableMove",
          "level": 8
        },
        {
          "move": "disable",
          "klass": "LevelLearnableMove",
          "level": 12
        },
        {
          "move": "brutal_swing",
          "klass": "LevelLearnableMove",
          "level": 16
        },
        {
          "move": "crafty_shield",
          "klass": "LevelLearnableMove",
          "level": 20
        },
        {
          "move": "hex",
          "klass": "LevelLearnableMove",
          "level": 24
        },
        {
          "move": "mean_look",
          "klass": "LevelLearnableMove",
          "level": 28
        },
        {
          "move": "slam",
          "klass": "LevelLearnableMove",
          "level": 32
        },
        {
          "move": "curse",
          "klass": "LevelLearnableMove",
          "level": 36
        },
        {
          "move": "shadow_ball",
          "klass": "LevelLearnableMove",
          "level": 40
        },
        {
          "move": "earthquake",
          "klass": "LevelLearnableMove",
          "level": 44
        },
        {
          "move": "guard_split",
          "klass": "LevelLearnableMove",
          "level": 48
        },
        {
          "move": "power_split",
          "klass": "LevelLearnableMove",
          "level": 48
        },
        {
          "move": "destiny_bond",
          "klass": "LevelLearnableMove",
          "level": 52
        },
        {
          "move": "earthquake",
          "klass": "TechLearnableMove"
        },
        {
          "move": "psychic",
          "klass": "TechLearnableMove"
        },
        {
          "move": "rest",
          "klass": "TechLearnableMove"
        },
        {
          "move": "rock_slide",
          "klass": "TechLearnableMove"
        },
        {
          "move": "substitute",
          "klass": "TechLearnableMove"
        },
        {
          "move": "thief",
          "klass": "TechLearnableMove"
        },
        {
          "move": "snore",
          "klass": "TechLearnableMove"
        },
        {
          "move": "protect",
          "klass": "TechLearnableMove"
        },
        {
          "move": "sandstorm",
          "klass": "TechLearnableMove"
        },
        {
          "move": "endure",
          "klass": "TechLearnableMove"
        },
        {
          "move": "attract",
          "klass": "TechLearnableMove"
        },
        {
          "move": "sleep_talk",
          "klass": "TechLearnableMove"
        },
        {
          "move": "safeguard",
          "klass": "TechLearnableMove"
        },
        {
          "move": "rain_dance",
          "klass": "TechLearnableMove"
        },
        {
          "move": "shadow_ball",
          "klass": "TechLearnableMove"
        },
        {
          "move": "will_o_wisp",
          "klass": "TechLearnableMove"
        },
        {
          "move": "memento",
          "klass": "BreedLearnableMove"
        },
        {
          "move": "facade",
          "klass": "TechLearnableMove"
        },
        {
          "move": "trick",
          "klass": "TechLearnableMove"
        },
        {
          "move": "skill_swap",
          "klass": "TechLearnableMove"
        },
        {
          "move": "imprison",
          "klass": "TechLearnableMove"
        },
        {
          "move": "fake_tears",
          "klass": "TechLearnableMove"
        },
        {
          "move": "rock_tomb",
          "klass": "TechLearnableMove"
        },
        {
          "move": "iron_defense",
          "klass": "TechLearnableMove"
        },
        {
          "move": "calm_mind",
          "klass": "TechLearnableMove"
        },
        {
          "move": "payback",
          "klass": "TechLearnableMove"
        },
        {
          "move": "toxic_spikes",
          "klass": "TechLearnableMove"
        },
        {
          "move": "dark_pulse",
          "klass": "TechLearnableMove"
        },
        {
          "move": "energy_ball",
          "klass": "TechLearnableMove"
        },
        {
          "move": "earth_power",
          "klass": "TechLearnableMove"
        },
        {
          "move": "nasty_plot",
          "klass": "TechLearnableMove"
        },
        {
          "move": "zen_headbutt",
          "klass": "TechLearnableMove"
        },
        {
          "move": "trick_room",
          "klass": "TechLearnableMove"
        },
        {
          "move": "wonder_room",
          "klass": "TechLearnableMove"
        },
        {
          "move": "round",
          "klass": "TechLearnableMove"
        },
        {
          "move": "ally_switch",
          "klass": "TechLearnableMove"
        },
        {
          "move": "hex",
          "klass": "TechLearnableMove"
        },
        {
          "move": "brutal_swing",
          "klass": "TechLearnableMove"
        },
        {
          "move": "poltergeist",
          "klass": "TutorLearnableMove"
        },
        {
          "move": "flash",
          "klass": "TechLearnableMove"
        }
      ]
    }
  ]
}